{
  "headers": {
    "content-type": "application/typescript; charset=utf-8",
    "x-amz-cf-id": "4Hj_VFcVnYIxTxlU7HhH6MlKhvPDuJhVgvnPrIMNUrmEwpM1AQiZMw==",
    "content-security-policy": "default-src 'none'; style-src 'unsafe-inline'; sandbox",
    "vary": "Accept-Encoding, Origin",
    "date": "Tue, 31 Jan 2023 14:48:33 GMT",
    "access-control-allow-origin": "*",
    "etag": "\"4ab82812778f74fd50c66a1708bd3f82\"",
    "via": "http/2 edgeproxy-h",
    "x-amz-cf-pop": "BOS50-C2",
    "last-modified": "Wed, 24 Aug 2022 21:03:19 GMT",
    "x-cache": "Miss from cloudfront",
    "x-amz-version-id": "sj4Up4LIc2WLocj7sY31Kcvf8wDz1Lw.",
    "cache-control": "public, max-age=31536000, immutable",
    "accept-ranges": "bytes",
    "content-length": "1270",
    "x-amz-replication-status": "COMPLETED",
    "server": "deno/gcp-us-east4"
  },
  "url": "https://deno.land/std@0.153.0/hash/mod.ts",
  "now": {
    "secs_since_epoch": 1675176512,
    "nanos_since_epoch": 390961122
  }
}