{
  "headers": {
    "cache-control": "public, max-age=31536000, immutable",
    "content-security-policy": "default-src 'none'; style-src 'unsafe-inline'; sandbox",
    "accept-ranges": "bytes",
    "last-modified": "Wed, 24 Aug 2022 21:03:17 GMT",
    "content-type": "application/typescript; charset=utf-8",
    "x-cache": "Miss from cloudfront",
    "x-amz-cf-id": "NA-V2BfJkCfRlEQXvi1C0lH9z1R-OffdwOVlNxiaQZCeHbg8G99u1w==",
    "vary": "Accept-Encoding, Origin",
    "x-amz-replication-status": "COMPLETED",
    "server": "deno/gcp-us-east4",
    "etag": "\"e6b02ebc2fd07c381cf28c41121b149d\"",
    "content-length": "868",
    "access-control-allow-origin": "*",
    "x-amz-version-id": "g9b8A69aeVhw7nSTl7KKypQSb.rocwER",
    "x-amz-cf-pop": "BOS50-C2",
    "date": "Tue, 31 Jan 2023 14:48:33 GMT",
    "via": "http/2 edgeproxy-h"
  },
  "url": "https://deno.land/std@0.153.0/collections/drop_last_while.ts",
  "now": {
    "secs_since_epoch": 1675176512,
    "nanos_since_epoch": 828890233
  }
}